{"company_name" : 
    {
        "Airbus" : 
            {
                "Airbus A220-100": {
                    "length": 35.0,
                    "capacity": 133,
                    "cockpit_crew": 2,
                    "body_type": "narrow-body",
                    "num_decks": 1,
                    "YOEIS": "2016",
                    "engine_manufacturer": "Pratt & Whitney",
                    "engine_name": "PW1500G",
                    "models_built": 108,
                    "topspeed": 829,
                    "number_engines": 2,
                    "wingspan": 35.1,
                    "width": 3.28,
                    "flight_range": 6390,
                    "engine_type": "High-bypass turbofan",
                    "first_flight": "2013",
                    "type": "Short to medium range",
                    "airline_companies_used": ["Delta Air Lines", "airBaltic", "Air France", "Air Canada", "JetBlue", "Korean Air", "Air Manas"],
                    "highest_altitude": 41000,
                    "aircraft_image": "https://upload.wikimedia.org/wikipedia/commons/thumb/4/4e/Airbus_A220.jpg/800px-Airbus_A220.jpg"
                },
                "Airbus A220-300": {
                    "length": 38.7,
                    "capacity": 160,
                    "cockpit_crew": 2,
                    "body_type": "narrow-body",
                    "num_decks": 1,
                    "YOEIS": "2016",
                    "engine_manufacturer": "Pratt & Whitney",
                    "engine_name": "PW1500G",
                    "models_built": 602,
                    "topspeed": 829,
                    "number_engines": 2,
                    "wingspan": 35.1,
                    "width": 3.28,
                    "flight_range": 6297,
                    "engine_type": "High-bypass turbofan",
                    "first_flight": "2015",
                    "type": "Short to medium range",
                    "airline_companies_used": ["Delta Air Lines", "airBaltic", "Air France", "Air Canada"],
                    "highest_altitude": 41000,
                    "aircraft_image": "https://upload.wikimedia.org/wikipedia/commons/thumb/4/4e/Airbus_A220.jpg/800px-Airbus_A220.jpg"
                },
            "Airbus A300": {
                "engine_manufacturer": "General Electric",
                "engine_name": "General Electric CF6",
                "models_built": 228,
                "topspeed": 897,
                "number_engines": 2,
                "wingspan": 44.84,
                "width": 5.64,
                "length": 54.08,
                "capacity": 345,
                "cockpit_crew": 2,
                "body_type": "wide-body",
                "num_decks": 1,
                "YOEIS": "1974",
                "flight_range": 5375,
                "engine_type": "High-bypass turbofan",
                "first_flight": "1972",
                "type": "Medium to long range",
                "airline_companies_used": ["FedEx Express", "UPS Airlines", "European Air Transport Leipzig", "Mahan Air", "MNG Airlines", "Solinair", "Iran Air", "Iran Airtour", "Qeshm Air"],
                "highest_altitude": 35000,
                "aircraft_image": "https://upload.wikimedia.org/wikipedia/commons/thumb/4/4e/Airbus_A300.jpg/800px-Airbus_A300.jpg"
            },
            "Airbus A300B1": {
                "length": 53.62,
                "capacity": 250,
                "cockpit_crew": 2,
                "body_type": "wide-body",
                "num_decks": 1,
                "YOEIS": "1974",
                "engine_manufacturer": "General Electric",
                "engine_name": "CF6-50",
                "models_built": 561,
                "topspeed": 871,
                "number_engines": 2,
                "wingspan": 44.84,
                "width": 5.28,
                "flight_range": 7500,
                "engine_type": "High-bypass turbofan",
                "first_flight": "1972",
                "type": "Medium to long range",
                "airline_companies_used": ["Air France", "Lufthansa", "Iberia", "Olympic Airways"],
                "highest_altitude": 35000,
                "aircraft_image": "https://upload.wikimedia.org/wikipedia/commons/6/62/Airbus_A300B4-2C_Air_France_AN1395988.jpg"
            },
            "Airbus A310": {
                "engine_manufacturer": "General Electric",
                "engine_name": "General Electric CF6",
                "models_built": 187,
                "topspeed": 897,
                "number_engines": 2,
                "wingspan": 43.9,
                "width": 5.28,
                "length": 46.66,
                "capacity": 279,
                "cockpit_crew": 2,
                "body_type": "wide-body",
                "num_decks": 1,
                "YOEIS": "1983",
                "flight_range": 6700,
                "engine_type": "High-bypass turbofan",
                "first_flight": "1982",
                "type": "Medium to long range",
                "airline_companies_used": ["Air India", "Aeroflot", "Air Calin", "Cyprus Airways", "Czech Airlines", "Kuwait Airways", "Air Afrique", "Pakistan International Airlines", "SATA"],
                "highest_altitude": 41100,
                "aircraft_image": "https://upload.wikimedia.org/wikipedia/commons/thumb/4/4e/Airbus_A310.jpg/800px-Airbus_A310.jpg"
            },
            "Airbus A318": {
                "engine_manufacturer": "General Electric",
                "engine_name": "CFM International CFM56",
                "models_built": 80,
                "topspeed": 900,
                "number_engines": 2,
                "wingspan": 34.1,
                "width": 3.95,
                "length": 31.45,
                "capacity": 132,
                "cockpit_crew": 2,
                "body_type": "narrow-body",
                "num_decks": 1,
                "YOEIS": "2003",
                "flight_range": 3100,
                "engine_type": "High-bypass turbofan",
                "first_flight": "2002",
                "type": "Short to medium range",
                "airline_companies_used": ["Air France", "TAROM"],
                "highest_altitude": 39000,
                "aircraft_image": "https://upload.wikimedia.org/wikipedia/commons/thumb/4/4e/Airbus_A318.jpg/800px-Airbus_A318.jpg"
            },
            "Airbus A319": {
                "engine_manufacturer": "CFM International",
                "engine_name": "CFM International CFM56",
                "models_built": 1500,
                "topspeed": 900,
                "number_engines": 2,
                "wingspan": 34.1,
                "width": 3.7,
                "length": 33.84,
                "capacity": 156,
                "cockpit_crew": 2,
                "body_type": "narrow-body",
                "num_decks": 1,
                "YOEIS": "1996",
                "flight_range": 3700,
                "engine_type": "High-bypass turbofan",
                "first_flight": "1995",
                "type": "Short to medium range",
                "airline_companies_used": ["easyJet", "American Airlines", "United Airlines", "Delta Air Lines", "Tibet Airlines", "Hunan Airlines", "Chengdu Airlines", "Shenzhen Airlines", "Myanmar Airways"],
                "highest_altitude": 41100,
                "aircraft_image": "https://upload.wikimedia.org/wikipedia/commons/thumb/4/4e/Airbus_A319.jpg/800px-Airbus_A319.jpg"
            },
            "Airbus A320": {
                "engine_manufacturer": "CFM International",
                "engine_name": "CFM International CFM56",
                "models_built": 17757,
                "topspeed": 903,
                "number_engines": 2,
                "wingspan": 35.8,
                "width": 3.7,
                "length": 37.57,
                "capacity": 186,
                "cockpit_crew": 2,
                "body_type": "narrow-body",
                "num_decks": 1,
                "YOEIS": "1988",
                "flight_range": 6100,
                "engine_type": "High-bypass turbofan",
                "first_flight": "1987",
                "type": "Short to medium range",
                "airline_companies_used": ["Delta Air Lines", "Lufthansa", "Air France", "British Airways", "Singapore Airlines", "Qatar Airways", "AirAsia", "Thai AirAsia", "Thai Vietjet", "China Southern Airlines"],
                "highest_altitude": 39100,
                "aircraft_image": "https://upload.wikimedia.org/wikipedia/commons/thumb/4/4e/Airbus_A320.jpg/800px-Airbus_A320.jpg"
            },
           
            
                "Airbus A320neo": {
                    "length": 37.57,
                    "capacity": 194,
                    "cockpit_crew": 2,
                    "body_type": "narrow-body",
                    "num_decks": 1,
                    "YOEIS": "2016",
                    "engine_manufacturer": "CFM International",
                    "engine_name": "LEAP-1A",
                    "models_built": 602,
                    "topspeed": 829,
                    "number_engines": 2,
                    "wingspan": 35.8,
                    "width": 3.95,
                    "flight_range": 6300,
                    "engine_type": "High-bypass turbofan",
                    "first_flight": "2014",
                    "type": "Short to medium range",
                    "airline_companies_used": ["IndiGo", "Wizz Air", "China Southern Airlines", "Frontier Airlines"],
                    "highest_altitude": 41000,
                    "aircraft_image": "https://upload.wikimedia.org/wikipedia/commons/thumb/4/4e/Airbus_A320neo.jpg/800px-Airbus_A320neo.jpg"
                },
                "Airbus A321": {
                    "length": 44.51,
                    "capacity": 236,
                    "cockpit_crew": 2,
                    "body_type": "narrow-body",
                    "num_decks": 1,
                    "YOEIS": "1994",
                    "engine_manufacturer": "IAE",
                    "engine_name": "V2500",
                    "models_built": 3145,
                    "topspeed": 828,
                    "number_engines": 2,
                    "wingspan": 34.1,
                    "width": 3.95,
                    "flight_range": 5600,
                    "engine_type": "High-bypass turbofan",
                    "first_flight": "1993",
                    "type": "Short to medium range",
                    "airline_companies_used": ["American Airlines", "Delta Air Lines", "China Southern Airlines", "Wizz Air"],
                    "highest_altitude": 41000,
                    "aircraft_image": "https://upload.wikimedia.org/wikipedia/commons/thumb/4/4e/Airbus_A321.jpg/800px-Airbus_A321.jpg"
                },
                "Airbus A321neo": {
                    "length": 44.51,
                    "capacity": 244,
                    "cockpit_crew": 2,
                    "body_type": "narrow-body",
                    "num_decks": 1,
                    "YOEIS": "2017",
                    "engine_manufacturer": "CFM International",
                    "engine_name": "LEAP-1A",
                    "models_built": 1339,
                    "topspeed": 828,
                    "number_engines": 2,
                    "wingspan": 35.8,
                    "width": 3.95,
                    "flight_range": 7400,
                    "engine_type": "High-bypass turbofan",
                    "first_flight": "2016",
                    "type": "Short to medium range",
                    "airline_companies_used": ["Wizz Air", "IndiGo", "American Airlines", "China Southern Airlines"],
                    "highest_altitude": 41000,
                    "aircraft_image": "https://upload.wikimedia.org/wikipedia/commons/thumb/4/4e/Airbus_A321neo.jpg/800px-Airbus_A321neo.jpg"
                },
                "Airbus A321XLR": {
                    "length": 44.51,
                    "capacity": 220,
                    "cockpit_crew": 2,
                    "body_type": "narrow-body",
                    "num_decks": 1,
                    "YOEIS": "2024",
                    "engine_manufacturer": "CFM International",
                    "engine_name": "LEAP-1A",
                    "models_built": 550,
                    "topspeed": 828,
                    "number_engines": 2,
                    "wingspan": 35.8,
                    "width": 3.95,
                    "flight_range": 8700,
                    "engine_type": "High-bypass turbofan",
                    "first_flight": "2023",
                    "type": "Long range",
                    "airline_companies_used": ["Aer Lingus", "Air Canada", "American Airlines", "Iberia", "Qantas", "United Airlines", "Air Arabia", "AirAsia X", "flynas", "IndiGo", "JetBlue"],
                    "highest_altitude": 41000,
                    "aircraft_image": "https://upload.wikimedia.org/wikipedia/commons/thumb/4/4e/Airbus_A321XLR.jpg/800px-Airbus_A321XLR.jpg"
            },
            "Airbus A330-200": {
                "length": 58.82,
                "capacity": 260,
                "cockpit_crew": 2,
                "body_type": "wide-body",
                "num_decks": 1,
                "YOEIS": "1998",
                "engine_manufacturer": "General Electric, Pratt & Whitney, Rolls-Royce",
                "engine_name": "CF6, PW4000, Trent 700",
                "models_built": 660,
                "topspeed": 880,
                "number_engines": 2,
                "wingspan": 60.3,
                "width": 5.64,
                "flight_range": 13400,
                "engine_type": "High-bypass turbofan",
                "first_flight": "1997",
                "type": "Long range",
                "airline_companies_used": ["Delta Air Lines", "Turkish Airlines", "China Eastern Airlines", "Cathay Pacific"],
                "highest_altitude": 41000
            },
            "Airbus A330-200F": {
                "length": 58.82,
                "capacity": 0,
                "cockpit_crew": 2,
                "body_type": "wide-body",
                "num_decks": 1,
                "YOEIS": "2010",
                "engine_manufacturer": "General Electric, Pratt & Whitney, Rolls-Royce",
                "engine_name": "CF6, PW4000, Trent 700",
                "models_built": 38,
                "topspeed": 871,
                "number_engines": 2,
                "wingspan": 60.3,
                "width": 5.64,
                "flight_range": 7400,
                "engine_type": "High-bypass turbofan",
                "first_flight": "2009",
                "type": "Freighter",
                "airline_companies_used": ["Etihad Cargo", "Turkish Cargo", "Qatar Airways Cargo", "MASkargo"],
                "highest_altitude": 41000
            },
            "Airbus A330-300": {
                "length": 63.66,
                "capacity": 290,
                "cockpit_crew": 2,
                "body_type": "wide-body",
                "num_decks": 1,
                "YOEIS": "1994",
                "engine_manufacturer": "General Electric, Pratt & Whitney, Rolls-Royce",
                "engine_name": "CF6, PW4000, Trent 700",
                "models_built": 816,
                "topspeed": 871,
                "number_engines": 2,
                "wingspan": 60.3,
                "width": 5.64,
                "flight_range": 11750,
                "engine_type": "High-bypass turbofan",
                "first_flight": "1992",
                "type": "Long range",
                "airline_companies_used": ["Delta Air Lines", "Turkish Airlines", "China Eastern Airlines", "Cathay Pacific"],
                "highest_altitude": 41000
            },
            "Airbus A330-800neo": {
                "length": 58.82,
                "capacity": 260,
                "cockpit_crew": 2,
                "body_type": "wide-body",
                "num_decks": 1,
                "YOEIS": "2020",
                "engine_manufacturer": "Rolls-Royce",
                "engine_name": "Trent 7000",
                "models_built": 15,
                "topspeed": 871,
                "number_engines": 2,
                "wingspan": 64,
                "width": 5.64,
                "flight_range": 15100,
                "engine_type": "High-bypass turbofan",
                "first_flight": "2018",
                "type": "Long range",
                "airline_companies_used": ["Kuwait Airways", "Uganda Airlines"],
                "highest_altitude": 41000
            },
            "Airbus A330-900neo": {
                "length": 63.66,
                "capacity": 300,
                "cockpit_crew": 2,
                "body_type": "wide-body",
                "num_decks": 1,
                "YOEIS": "2018",
                "engine_manufacturer": "Rolls-Royce",
                "engine_name": "Trent 7000",
                "models_built": 131,
                "topspeed": 871,
                "number_engines": 2,
                "wingspan": 64,
                "width": 5.64,
                "flight_range": 13330,
                "engine_type": "High-bypass turbofan",
                "first_flight": "2017",
                "type": "Long range",
                "airline_companies_used": ["Delta Air Lines", "TAP Air Portugal", "AirAsia X", "Lion Air"],
                "highest_altitude": 41000
            },            
            "Airbus A340-200": {
                "length": 59.39,
                "capacity": 250,
                "cockpit_crew": 2,
                "body_type": "wide-body",
                "num_decks": 1,
                "YOEIS": "1993",
                "engine_manufacturer": "CFM International",
                "engine_name": "CFM56-5C3/G4",
                "models_built": 28,
                "topspeed": 915,
                "number_engines": 4,
                "wingspan": 60.30,
                "width": 5.64,
                "flight_range": 12400,
                "engine_type": "High-bypass turbofan",
                "first_flight": "1992",
                "type": "Long range",
                "airline_companies_used": ["Lufthansa", "Air France"],
                "highest_altitude": 41000
            },
            "Airbus A340-300": {
                "length": 63.69,
                "capacity": 290,
                "cockpit_crew": 2,
                "body_type": "wide-body",
                "num_decks": 1,
                "YOEIS": "1993",
                "engine_manufacturer": "CFM International",
                "engine_name": "CFM56-5C4",
                "models_built": 218,
                "topspeed": 915,
                "number_engines": 4,
                "wingspan": 60.30,
                "width": 5.64,
                "flight_range": 13500,
                "engine_type": "High-bypass turbofan",
                "first_flight": "1991",
                "type": "Long range",
                "airline_companies_used": ["Lufthansa", "Air France", "Iberia", "South African Airways"],
                "highest_altitude": 41000
            },
            "Airbus A340-500": {
                "length": 67.90,
                "capacity": 310,
                "cockpit_crew": 2,
                "body_type": "wide-body",
                "num_decks": 1,
                "YOEIS": "2002",
                "engine_manufacturer": "Rolls-Royce",
                "engine_name": "Trent 553-61",
                "models_built": 32,
                "topspeed": 915,
                "number_engines": 4,
                "wingspan": 63.45,
                "width": 5.64,
                "flight_range": 16699,
                "engine_type": "High-bypass turbofan",
                "first_flight": "2002",
                "type": "Ultra-long range",
                "airline_companies_used": ["Emirates", "Etihad Airways"],
                "highest_altitude": 41000
            },
            "Airbus A340-600": {
                "length": 75.36,
                "capacity": 370,
                "cockpit_crew": 2,
                "body_type": "wide-body",
                "num_decks": 1,
                "YOEIS": "2002",
                "engine_manufacturer": "Rolls-Royce",
                "engine_name": "Trent 556-61",
                "models_built": 97,
                "topspeed": 915,
                "number_engines": 4,
                "wingspan": 63.45,
                "width": 5.64,
                "flight_range": 14450,
                "engine_type": "High-bypass turbofan",
                "first_flight": "2001",
                "type": "Long range",
                "airline_companies_used": ["Lufthansa", "Virgin Atlantic", "Iberia", "South African Airways"],
                "highest_altitude": 41000
            },
            "Airbus A350-900": {
                "length": 66.8,
                "capacity": 350,
                "cockpit_crew": 2,
                "body_type": "wide-body",
                "num_decks": 1,
                "YOEIS": "2015",
                "engine_manufacturer": "Rolls-Royce",
                "engine_name": "Rolls-Royce Trent XWB",
                "models_built": 602,
                "topspeed": 945,
                "number_engines": 2,
                "wingspan": 64.75,
                "width": 5.96,
                "flight_range": 15000,
                "engine_type": "High-bypass turbofan",
                "first_flight": "2013",
                "type": "Long range",
                "airline_companies_used": ["Singapore Airlines", "Qatar Airways", "Cathay Pacific", "Delta Air Lines"],
                "highest_altitude": 41000,
                "aircraft_image": "https://upload.wikimedia.org/wikipedia/commons/thumb/4/4e/Airbus_A350_XWB.jpg/800px-Airbus_A350_XWB.jpg"
            },
            "Airbus A350-1000": {
                "length": 73.79,
                "capacity": 410,
                "cockpit_crew": 2,
                "body_type": "wide-body",
                "num_decks": 1,
                "YOEIS": "2018",
                "engine_manufacturer": "Rolls-Royce",
                "engine_name": "Rolls-Royce Trent XWB",
                "models_built": 602,
                "topspeed": 945,
                "number_engines": 2,
                "wingspan": 64.75,
                "width": 5.96,
                "flight_range": 16100,
                "engine_type": "High-bypass turbofan",
                "first_flight": "2017",
                "type": "Long range",
                "airline_companies_used": ["Singapore Airlines", "Qatar Airways", "Cathay Pacific", "Delta Air Lines"],
                "highest_altitude": 41000,
                "aircraft_image": "https://upload.wikimedia.org/wikipedia/commons/thumb/4/4e/Airbus_A350_XWB.jpg/800px-Airbus_A350_XWB.jpg"
            },
            "Airbus A350 XWB": {
                "length": 73.78,
                "capacity": 410,
                "cockpit_crew": 2,
                "body_type": "wide-body",
                "num_decks": 1,
                "YOEIS": "2015",
                "engine_manufacturer": "Rolls-Royce",
                "engine_name": "Rolls-Royce Trent XWB",
                "models_built": 602,
                "topspeed": 945,
                "number_engines": 2,
                "wingspan": 64.8,
                "width": 5.96,
                "flight_range": 15000,
                "engine_type": "High-bypass turbofan",
                "first_flight": "2013",
                "type": "Long range",
                "airline_companies_used": ["Singapore Airlines", "Qatar Airways", "Cathay Pacific", "Delta Air Lines"],
                "highest_altitude": 41000,
                "aircraft_image": "https://upload.wikimedia.org/wikipedia/commons/thumb/4/4e/Airbus_A350_XWB.jpg/800px-Airbus_A350_XWB.jpg"
            },
            
            
            "Airbus A380-800": {
                "length": 72.72,
                "capacity": 853,
                "cockpit_crew": 2,
                "body_type": "wide-body",
                "num_decks": 2,
                "YOEIS": "2007",
                "engine_manufacturer": "Engine Alliance, Rolls-Royce",
                "engine_name": "GP7200, Trent 900",
                "models_built": 254,
                "topspeed": 1020,
                "number_engines": 4,
                "wingspan": 79.75,
                "width": 7.14,
                "flight_range": 15200
            },
            "Airbus A380F": {
                "length": 72.72,
                "capacity": 150,
                "cockpit_crew": 2,
                "body_type": "wide-body",
                "num_decks": 3,
                "YOEIS": "N/A",
                "engine_manufacturer": "Engine Alliance, Rolls-Royce",
                "engine_name": "GP7200, Trent 900",
                "models_built": 0,
                "topspeed": 1020,
                "number_engines": 4,
                "wingspan": 79.75,
                "width": 7.14,
                "flight_range": 10400
            },
            "Airbus Beluga": {
                "engine_manufacturer": "General Electric",
                "engine_name": "General Electric CF6",
                "models_built": 5,
                "topspeed": 865,
                "number_engines": 2,
                "wingspan": 44.84,
                "width": 7.1,
                "length": 56.16,
                "capacity": 0,
                "cockpit_crew": 2,
                "body_type": "wide-body",
                "num_decks": 1,
                "YOEIS": "1995",
                "flight_range": 2770,
                "engine_type": "High-bypass turbofan",
                "first_flight": "1994",
                "type": "Outsize cargo freight aircraft",
                "airline_companies_used": ["Airbus Transport International"],
                "highest_altitude": 35000,
                "aircraft_image": "https://upload.wikimedia.org/wikipedia/commons/thumb/4/4e/Airbus_Beluga.jpg/800px-Airbus_Beluga.jpg"
            }
            },
            
        "Boeing" :
            {
                "Boeing 247": {
                    "engine_manufacturer": "Pratt & Whitney",
                    "engine_name": "Wasp",
                    "models_built": 75,
                    "length": 15.72,
                    "capacity": 10,
                    "cockpit_crew": 3,
                    "body_type": "narrow-body",
                    "num_decks": 1,
                    "YOEIS": "1933",
                    "topspeed": 322,
                    "number_engines": 2,
                    "wingspan": 22.56,
                    "width": 3.05,
                    "flight_range": 1200,
                    "engine_type": "Radial engine",
                    "first_flight": "1933",
                    "type": "Short range",
                    "airline_companies_used": ["United Airlines"],
                    "highest_altitude": 25000,
                    "aircraft_image": "https://upload.wikimedia.org/wikipedia/commons/7/74/Boeing_247D_in_flight_c1935.jpg"
                },
                "Boeing 307 Stratoliner": {
                    "length": 22.66,
                    "capacity": 33,
                    "cockpit_crew": 3,
                    "body_type": "narrow-body",
                    "num_decks": 1,
                    "YOEIS": "1940",
                    "engine_manufacturer": "Wright",
                    "engine_name": "Cyclone 9",
                    "models_built": 10,
                    "topspeed": 396,
                    "number_engines": 4,
                    "wingspan": 32.7,
                    "width": 3.35,
                    "flight_range": 2400,
                    "engine_type": "Radial engine",
                    "first_flight": "1938",
                    "type": "Long range",
                    "airline_companies_used": ["Pan American Airways", "TWA"],
                    "highest_altitude": 23000,
                    "aircraft_image": "https://upload.wikimedia.org/wikipedia/commons/7/72/Boeing_307,_TWA_AN0201416.jpg"
                },
                "Boeing 707": {
                    "engine_manufacturer": "Pratt & Whitney",
                    "engine_name": "JT3D-3B",
                    "models_built": 865,
                    "topspeed": 1004,
                    "number_engines": 4,
                    "length": 46.61,
                    "capacity": 189,
                    "cockpit_crew": 3,
                    "body_type": "narrow-body",
                    "num_decks": 1,
                    "YOEIS": "1958",
                    "wingspan": 44.42,
                    "width": 3.76,
                    "flight_range": 7255,
                    "engine_type": "Turbojet",
                    "first_flight": "1957",
                    "type": "Long range",
                    "airline_companies_used": ["Pan American World Airways", "Trans World Airlines"],
                    "highest_altitude": 36000,
                    "aircraft_image": "https://upload.wikimedia.org/wikipedia/commons/4/4f/Boeing_707-138B_AN0979266.jpg"
                },
                "Boeing 707-100B": {
                    "length": 44.22,
                    "capacity": 189,
                    "cockpit_crew": 3,
                    "body_type": "narrow-body",
                    "num_decks": 1,
                    "YOEIS": "1958",
                    "engine_manufacturer": "Pratt & Whitney",
                    "engine_name": "JT3D",
                    "models_built": 856,
                    "topspeed": 1002,
                    "number_engines": 4,
                    "wingspan": 39.9,
                    "width": 3.76,
                    "flight_range": 7200,
                    "engine_type": "Low-bypass turbofan",
                    "first_flight": "1957",
                    "type": "Long range",
                    "airline_companies_used": ["Pan American World Airways", "TWA", "American Airlines", "United Airlines"],
                    "highest_altitude": 42000,
                    "aircraft_image": "https://upload.wikimedia.org/wikipedia/commons/4/4c/Boeing_707-123B_AN2159666.jpg"
                },
                "Boeing 717": {
                    "engine_manufacturer": "Rolls-Royce Deutschland",
                    "engine_name": "BR700-715C1-30",
                    "models_built": 156,
                    "topspeed": 811,
                    "number_engines": 2,
                    "wingspan": 28.45,
                    "width": 3.14,
                    "length": 37.81,
                    "capacity": 134,
                    "cockpit_crew": 2,
                    "body_type": "narrow-body",
                    "num_decks": 1,
                    "YOEIS": "1999",
                    "flight_range": 2645,
                    "engine_type": "Turbofan",
                    "first_flight": "1998",
                    "type": "Short to medium range",
                    "airline_companies_used": ["Southwest Airlines", "Hawaiian Airlines"],
                    "highest_altitude": 37000,
                    "aircraft_image": "https://upload.wikimedia.org/wikipedia/commons/7/72/Boeing_717-2BD%2C_AirTran_Airways_AN2153694.jpg"
                },
                "Boeing 727": {
                    "engine_manufacturer": "Pratt & Whitney",
                    "engine_name": "JT8D-7",
                    "models_built": 1832,
                    "topspeed": 943,
                    "number_engines": 3,
                    "wingspan": 32.92,
                    "width": 3.8,
                    "length": 46.68,
                    "capacity": 189,
                    "cockpit_crew": 3,
                    "body_type": "narrow-body",
                    "num_decks": 1,
                    "YOEIS": "1964",
                    "flight_range": 2700,
                    "engine_type": "Low-bypass turbofan",
                    "first_flight": "1963",
                    "type": "Short to medium range",
                    "airline_companies_used": ["United Airlines", "American Airlines"],
                    "highest_altitude": 42000,
                    "aircraft_image": "https://upload.wikimedia.org/wikipedia/commons/6/60/Boeing_727-22%2C_United_Airlines_JP5956342.jpg"
                },
                "Boeing 737-100": {
                    "engine_manufacturer": "Pratt & Whitney",
                    "engine_name": "JT8D-7",
                    "models_built": 30,
                    "topspeed": 943,
                    "number_engines": 2,
                    "wingspan": 28.35,
                    "width": 3.76,
                   
                        "length": 28.65,
                        "capacity": 85,
                        "cockpit_crew": 2,
                        "body_type": "narrow-body",
                        "num_decks": 1,
                        "YOEIS": "1968",
                    "flight_range": 2855,
                    "engine_type": "Low-bypass turbofan",
                    "first_flight": "1967",
                    "type": "Short to medium range",
                    "airline_companies_used": ["Lufthansa"],
                    "highest_altitude": 35000,
                    "aircraft_image": "https://upload.wikimedia.org/wikipedia/commons/0/0a/Lufthansa_Boeing_737-100_%28D-ABEA%29_at_FRA.jpg"
                },
                "Boeing 737-200": {
                    "engine_manufacturer": "Pratt & Whitney",
                    "engine_name": "JT8D-9A",
                    "models_built": 1095,
                    "topspeed": 943,
                    "number_engines": 2,
                    "wingspan": 28.35,
                    "width": 3.76,
                    "length": 30.53,
                    "capacity": 115,
                    "cockpit_crew": 2,
                    "body_type": "narrow-body",
                    "num_decks": 1,
                    "YOEIS": "1968",
                    "flight_range": 4260,
                    "engine_type": "Low-bypass turbofan",
                    "first_flight": "1967",
                    "type": "Short to medium range",
                    "airline_companies_used": ["United Airlines"],
                    "highest_altitude": 35000,
                    "aircraft_image": "https://upload.wikimedia.org/wikipedia/commons/8/89/Boeing_737-200_Advanced_AN1241006.jpg"
                },
                "Boeing 737-300": {
                    "engine_manufacturer": "CFM International",
                    "engine_name": "CFM56-3B2",
                    "models_built": 1113,
                    "topspeed": 946,
                    "number_engines": 2,
                    "wingspan": 28.88,
                    "width": 3.76,
                    "length": 33.40,
                    "capacity": 149,
                    "cockpit_crew": 2,
                    "body_type": "narrow-body",
                    "num_decks": 1,
                    "YOEIS": "1984",
                    "flight_range": 5463,
                    "engine_type": "High-bypass turbofan",
                    "first_flight": "1984",
                    "type": "Short to medium range",
                    "airline_companies_used": ["Southwest Airlines"],
                    "highest_altitude": 37000,
                    "aircraft_image": "https://upload.wikimedia.org/wikipedia/commons/2/22/Boeing_737-300%2C_Southwest_Airlines_JP5976346.jpg"
                },
                "Boeing 737-400": {
                    "engine_manufacturer": "CFM International",
                    "engine_name": "CFM56-3C1",
                    "models_built": 486,
                    "topspeed": 943,
                    "number_engines": 2,
                    "wingspan": 28.88,
                    "width": 3.76,
                    "length": 36.45,
                    "capacity": 168,
                    "cockpit_crew": 2,
                    "body_type": "narrow-body",
                    "num_decks": 1,
                    "YOEIS": "1988",
                    "flight_range": 4260,
                    "engine_type": "High-bypass turbofan",
                    "first_flight": "1988",
                    "type": "Short to medium range",
                    "airline_companies_used": ["Piedmont Airlines"],
                    "highest_altitude": 37000,
                    "aircraft_image": "https://upload.wikimedia.org/wikipedia/commons/7/72/Boeing_737-400%2C_Britannia_Airways_AN0202912.jpg"
                },
                "Boeing 737-500": {
                    "engine_manufacturer": "CFM International",
                    "engine_name": "CFM56-3B1",
                    "models_built": 389,
                    "topspeed": 946,
                    "number_engines": 2,
                    "wingspan": 28.88,
                    "width": 3.76,
                    "length": 31.01,
                    "capacity": 132,
                    "cockpit_crew": 2,
                    "body_type": "narrow-body",
                    "num_decks": 1,
                    "YOEIS": "1990",
                    "flight_range": 5463,
                    "engine_type": "High-bypass turbofan",
                    "first_flight": "1989",
                    "type": "Short to medium range",
                    "airline_companies_used": ["Southwest Airlines"],
                    "highest_altitude": 37000,
                    "aircraft_image": "https://upload.wikimedia.org/wikipedia/commons/7/72/Boeing_737-500%2C_Air_Baltic_AN0202912.jpg"
                },
                "Boeing 737-600": {
                    "engine_manufacturer": "CFM International",
                    "engine_name": "CFM56-7B22",
                    "models_built": 69,
                    "topspeed": 943,
                    "number_engines": 2,
                    "wingspan": 34.31,
                    "width": 3.76,
                    "length": 31.24,
                    "capacity": 132,
                    "cockpit_crew": 2,
                    "body_type": "narrow-body",
                    "num_decks": 1,
                    "YOEIS": "1998",
                    "flight_range": 5463,
                    "engine_type": "High-bypass turbofan",
                    "first_flight": "1998",
                    "type": "Short to medium range",
                    "airline_companies_used": ["Scandinavian Airlines"],
                    "highest_altitude": 41000,
                    "aircraft_image": "https://upload.wikimedia.org/wikipedia/commons/7/72/Boeing_737-600%2C_SAS_-_Scandinavian_Airlines_AN0202912.jpg"
                },
                
                    "Boeing 737-700": {
                        "engine_manufacturer": "CFM International",
                        "engine_name": "CFM56-7B24",
                        "models_built": 1124,
                        "topspeed": 946,
                        "number_engines": 2,
                        "wingspan": 34.32,
                        "width": 3.76,
                        "length": 33.63,
                        "capacity": 149,
                        "cockpit_crew": 2,
                        "body_type": "narrow-body",
                        "num_decks": 1,
                        "YOEIS": "1997",
                        "flight_range": 6482,
                        "engine_type": "High-bypass turbofan",
                        "first_flight": "1997",
                        "type": "Short to medium range",
                        "airline_companies_used": ["Southwest Airlines", "United Airlines"],
                        "highest_altitude": 41000,
                        "aircraft_image": "https://upload.wikimedia.org/wikipedia/commons/7/72/Boeing_737-700.jpg"
                    },
                    "Boeing 737-800": {
                        "engine_manufacturer": "CFM International",
                        "engine_name": "CFM56-7B27",
                        "models_built": 4991,
                        "topspeed": 946,
                        "number_engines": 2,
                        "wingspan": 34.32,
                        "width": 3.76,
                        "length": 39.47,
                        "capacity": 189,
                        "cockpit_crew": 2,
                        "body_type": "narrow-body",
                        "num_decks": 1,
                        "YOEIS": "1998",
                        "flight_range": 5463,
                        "engine_type": "High-bypass turbofan",
                        "first_flight": "1997",
                        "type": "Short to medium range",
                        "airline_companies_used": ["Ryanair", "American Airlines"],
                        "highest_altitude": 41000,
                        "aircraft_image": "https://upload.wikimedia.org/wikipedia/commons/7/72/Boeing_737-800.jpg"
                    },
                    "Boeing 737-900": {
                        "engine_manufacturer": "CFM International",
                        "engine_name": "CFM56-7B27",
                        "models_built": 52,
                        "topspeed": 946,
                        "number_engines": 2,
                        "wingspan": 34.32,
                        "width": 3.76,
                        "length": 42.11,
                        "capacity": 220,
                        "cockpit_crew": 2,
                        "body_type": "narrow-body",
                        "num_decks": 1,
                        "YOEIS": "2000",
                        "flight_range": 5463,
                        "engine_type": "High-bypass turbofan",
                        "first_flight": "2000",
                        "type": "Short to medium range",
                        "airline_companies_used": ["Alaska Airlines", "United Airlines"],
                        "highest_altitude": 41000,
                        "aircraft_image": "https://upload.wikimedia.org/wikipedia/commons/7/72/Boeing_737-900.jpg"
                    },
                    "Boeing 737 MAX": {
                        "engine_manufacturer": "CFM International",
                        "engine_name": "LEAP-1B",
                        "models_built": 450,
                        "topspeed": 839,
                        "number_engines": 2,
                        "wingspan": 35.92,
                        "width": 3.54,
                        "length": 43.8,
                        "capacity": 230,
                        "cockpit_crew": 2,
                        "body_type": "narrow-body",
                        "num_decks": 1,
                        "YOEIS": "2017",
                        "flight_range": 6570,
                        "engine_type": "High-bypass turbofan",
                        "first_flight": "2016",
                        "type": "Short to medium range",
                        "airline_companies_used": ["Southwest Airlines", "Air Canada"],
                        "highest_altitude": 41000,
                        "aircraft_image": "https://upload.wikimedia.org/wikipedia/commons/7/72/Boeing_737_MAX.jpg"
                    },
                    "Boeing 747-100": {
                        "engine_manufacturer": "Pratt & Whitney",
                        "engine_name": "JT9D-7A",
                        "models_built": 167,
                        "topspeed": 988,
                        "number_engines": 4,
                        "wingspan": 59.64,
                        "width": 6.1,
                        "length": 70.66,
                        "capacity": 480,
                        "cockpit_crew": 3,
                        "body_type": "wide-body",
                        "num_decks": 2,
                        "YOEIS": "1970",
                        "flight_range": 9200,
                        "engine_type": "Low-bypass turbofan",
                        "first_flight": "1969",
                        "type": "Long range",
                        "airline_companies_used": ["Pan American World Airways"],
                        "highest_altitude": 45000,
                        "aircraft_image": "https://upload.wikimedia.org/wikipedia/commons/7/72/Boeing_747-100.jpg"
                    },
                    "Boeing 747-200": {
                        "engine_manufacturer": "Pratt & Whitney",
                        "engine_name": "JT9D-7Q",
                        "models_built": 393,
                        "topspeed": 988,
                        "number_engines": 4,
                        "wingspan": 59.64,
                        "width": 6.1,
                        "length": 70.66,
                        "capacity": 480,
                        "cockpit_crew": 3,
                        "body_type": "wide-body",
                        "num_decks": 2,
                        "YOEIS": "1971",
                        "flight_range": 12200,
                        "engine_type": "Low-bypass turbofan",
                        "first_flight": "1971",
                        "type": "Long range",
                        "airline_companies_used": ["British Airways"],
                        "highest_altitude": 45000,
                        "aircraft_image": "https://upload.wikimedia.org/wikipedia/commons/7/72/Boeing_747-200.jpg"
                    },
                    "Boeing 747-400": {
                        "engine_manufacturer": "General Electric",
                        "engine_name": "CF6-80C2B1F",
                        "models_built": 694,
                        "topspeed": 988,
                        "number_engines": 4,
                        "wingspan": 64.44,
                        "width": 6.1,
                        "length": 70.66,
                        "capacity": 660,
                        "cockpit_crew": 2,
                        "body_type": "wide-body",
                        "num_decks": 2,
                        "YOEIS": "1989",
                        "flight_range": 13430,
                        "engine_type": "High-bypass turbofan",
                        "first_flight": "1988",
                        "type": "Long range",
                        "airline_companies_used": ["British Airways", "Lufthansa"],
                        "highest_altitude": 45000,
                        "aircraft_image": "https://upload.wikimedia.org/wikipedia/commons/7/72/Boeing_747-400.jpg"
                    },
                    "Boeing 747-8": {
                        "engine_manufacturer": "General Electric",
                        "engine_name": "GEnx-2B67",
                        "models_built": 155,
                        "topspeed": 988,
                        "number_engines": 4,
                        "wingspan": 68.45,
                        "width": 6.1,
                        "length": 76.25,
                        "capacity": 700,
                        "cockpit_crew": 2,
                        "body_type": "wide-body",
                        "num_decks": 2,
                        "YOEIS": "2012",
                        "flight_range": 14815,
                        "engine_type": "High-bypass turbofan",
                        "first_flight": "2010",
                        "type": "Long range",
                        "airline_companies_used": ["Lufthansa", "Korean Air"],
                        "highest_altitude": 43000,
                        "aircraft_image": "https://upload.wikimedia.org/wikipedia/commons/7/72/Boeing_747-8.jpg"
                    },
                    "Boeing 757": {
                        "engine_manufacturer": "Rolls-Royce",
                        "engine_name": "RB211-535E4",
                        "models_built": 1050,
                        "topspeed": 982,
                        "number_engines": 2,
                        "wingspan": 38.05,
                        "width": 3.54,
                        "length": 47.32,
                        "capacity": 239,
                        "cockpit_crew": 2,
                        "body_type": "narrow-body",
                        "num_decks": 1,
                        "YOEIS": "1983",
                        "flight_range": 7222,
                        "engine_type": "High-bypass turbofan",
                        "first_flight": "1982",
                        "type": "Short to medium range",
                        "airline_companies_used": ["Delta Air Lines", "United Airlines"],
                        "highest_altitude": 42000,
                        "aircraft_image": "https://upload.wikimedia.org/wikipedia/commons/7/72/Boeing_757.jpg"
                    },
                    "Boeing 767-200": {
                        "engine_manufacturer": "General Electric",
                        "engine_name": "CF6-80A",
                        "models_built": 128,
                        "topspeed": 851,
                        "number_engines": 2,
                        "wingspan": 47.57,
                        "width": 4.72,
                        "length": 48.51,
                        "capacity": 255,
                        "cockpit_crew": 2,
                        "body_type": "wide-body",
                        "num_decks": 1,
                        "YOEIS": "1982",
                        "flight_range": 7222,
                        "engine_type": "High-bypass turbofan",
                        "first_flight": "1981",
                        "type": "Medium to long range",
                        "airline_companies_used": ["Delta Air Lines", "United Airlines"],
                        "highest_altitude": 43000,
                        "aircraft_image": "https://upload.wikimedia.org/wikipedia/commons/7/72/Boeing_767-200.jpg"
                    },
                    "Boeing 767-300": {
                        "engine_manufacturer": "General Electric",
                        "engine_name": "CF6-80C2B2F",
                        "models_built": 1040,
                        "topspeed": 850,
                        "number_engines": 2,
                        "wingspan": 47.57,
                        "width": 4.72,
                        "length": 54.94,
                        "capacity": 269,
                        "cockpit_crew": 2,
                        "body_type": "wide-body",
                        "num_decks": 1,
                        "YOEIS": "1986",
                        "flight_range": 11107,
                        "engine_type": "High-bypass turbofan",
                        "first_flight": "1986",
                        "type": "Medium to long range",
                        "airline_companies_used": ["Delta Air Lines", "FedEx Express", "UPS Airlines", "United Airlines"],
                        "highest_altitude": 43100,
                        "aircraft_image": "https://upload.wikimedia.org/wikipedia/commons/4/4e/Boeing_767-300.jpg"
                    },
                    "Boeing 767-400ER": {
                        "engine_manufacturer": "Pratt & Whitney",
                        "engine_name": "PW4060",
                        "models_built": 37,
                        "topspeed": 850,
                        "number_engines": 2,
                        "wingspan": 51.9,
                        "width": 4.72,
                        "length": 61.37,
                        "capacity": 296,
                        "cockpit_crew": 2,
                        "body_type": "wide-body",
                        "num_decks": 1,
                        "YOEIS": "2000",
                        "flight_range": 10415,
                        "engine_type": "High-bypass turbofan",
                        "first_flight": "2000",
                        "type": "Medium to long range",
                        "airline_companies_used": ["United Airlines", "Delta Air Lines"],
                        "highest_altitude": 43100,
                        "aircraft_image": "https://upload.wikimedia.org/wikipedia/commons/4/4e/Boeing_767-400ER.jpg"
                    },
                    "Boeing 787-8": {
                        "engine_manufacturer": "General Electric",
                        "engine_name": "GEnx-1B64",
                        "models_built": 397,
                        "topspeed": 954,
                        "number_engines": 2,
                        "wingspan": 60.12,
                        "width": 5.49,
                        "length": 56.72,
                        "capacity": 242,
                        "cockpit_crew": 2,
                        "body_type": "wide-body",
                        "num_decks": 1,
                        "YOEIS": "2011",
                        "flight_range": 13804,
                        "engine_type": "High-bypass turbofan",
                        "first_flight": "2011",
                        "type": "Long range",
                        "airline_companies_used": ["All Nippon Airways", "United Airlines", "American Airlines", "Qatar Airways", "Japan Airlines", "Etihad Airways", "Hainan Airlines", "Air Canada", "British Airways", "Ethiopian Airlines", "Air India"],
                        "highest_altitude": 43100,
                        "aircraft_image": "https://upload.wikimedia.org/wikipedia/commons/4/4e/Boeing_787-8.jpg"
                    },
                    "Boeing 787-9": {
                        "engine_manufacturer": "General Electric",
                        "engine_name": "GEnx-1B74",
                        "models_built": 621,
                        "topspeed": 954,
                        "number_engines": 2,
                        "wingspan": 60.12,
                        "width": 5.49,
                        "length": 62.81,
                        "capacity": 290,
                        "cockpit_crew": 2,
                        "body_type": "wide-body",
                        "num_decks": 1,
                        "YOEIS": "2014",
                        "flight_range": 14140,
                        "engine_type": "High-bypass turbofan",
                        "first_flight": "2013",
                        "type": "Long range",
                        "airline_companies_used": ["All Nippon Airways", "United Airlines", "American Airlines", "Qatar Airways", "Japan Airlines", "Etihad Airways", "Hainan Airlines", "Air Canada", "British Airways", "Ethiopian Airlines", "Air India"],
                        "highest_altitude": 43100,
                        "aircraft_image": "https://upload.wikimedia.org/wikipedia/commons/4/4e/Boeing_787-9.jpg"
                    },
                    "Boeing 787-10": {
                        "engine_manufacturer": "General Electric",
                        "engine_name": "GEnx-1B76",
                        "models_built": 97,
                        "topspeed": 954,
                        "number_engines": 2,
                        "wingspan": 60.12,
                        "width": 5.49,
                        "length": 68.28,
                        "capacity": 330,
                        "cockpit_crew": 2,
                        "body_type": "wide-body",
                        "num_decks": 1,
                        "YOEIS": "2017",
                        "flight_range": 11730,
                        "engine_type": "High-bypass turbofan",
                        "first_flight": "2017",
                        "type": "Long range",
                        "airline_companies_used": ["Singapore Airlines", "Etihad Airways", "United Airlines"],
                        "highest_altitude": 43100,
                        "aircraft_image": "https://upload.wikimedia.org/wikipedia/commons/4/4e/Boeing_787-10.jpg"
                    }
                
        }
    }
}
